cosinorage/__init__.py
cosinorage/bioages/__init__.py
cosinorage/bioages/cosinorage.py
cosinorage/datahandlers/__init__.py
cosinorage/datahandlers/datahandler.py
cosinorage/datahandlers/galaxydatahandler.py
cosinorage/datahandlers/genericdatahandler.py
cosinorage/datahandlers/nhanesdatahandler.py
cosinorage/datahandlers/ukbdatahandler.py
cosinorage/datahandlers/utils/__init__.py
cosinorage/datahandlers/utils/calc_enmo.py
cosinorage/datahandlers/utils/calibration.py
cosinorage/datahandlers/utils/filtering.py
cosinorage/datahandlers/utils/frequency_detection.py
cosinorage/datahandlers/utils/galaxy_binary.py
cosinorage/datahandlers/utils/galaxy_csv.py
cosinorage/datahandlers/utils/generic.py
cosinorage/datahandlers/utils/nhanes.py
cosinorage/datahandlers/utils/noise_removal.py
cosinorage/datahandlers/utils/ukb.py
cosinorage/datahandlers/utils/visualization.py
cosinorage/datahandlers/utils/wear_detection.py
cosinorage/features/__init__.py
cosinorage/features/bulk_features.py
cosinorage/features/features.py
cosinorage/features/utils/__init__.py
cosinorage/features/utils/cosinor_analysis.py
cosinorage/features/utils/dashboard.py
cosinorage/features/utils/nonparam_analysis.py
cosinorage/features/utils/physical_activity_metrics.py
cosinorage/features/utils/rescaling.py
cosinorage/features/utils/sleep_metrics.py
cosinorage/features/utils/visualization.py
cosinorage-1.0.5.dist-info/licenses/LICENSE
cosinorage-1.0.5.dist-info/METADATA
cosinorage-1.0.5.dist-info/WHEEL
cosinorage-1.0.5.dist-info/top_level.txt
cosinorage-1.0.5.dist-info/RECORD
